{
    "chartOptions": {
        "patients": {
            "legendMapping": {
                "ecdc-bridgehead-test1": "Test1"
            }
        },
        "gender": {
            "legendMapping": {
                "male": "Male",
                "female": "Female",
                "unknown": "Unknown",
                "other": "Other"
            }
        },
        "age_of_patient": {
            "hintText": [
                "By patients with multiple diagnoses, results may be shown that lie outside the search criteria. "
            ]
        }
    },
    "tableOptions": {
        "headerData": [
            {
                "title": "Node",
                "dataKey": "site"
            },
            {
                "title": "N Isolates (distinct)",
                "dataKey": "patients"
            }
        ]
    }
}